frprint/__init__.py
frprint/frprint.py
frprint-1.2.3.dist-info/METADATA
frprint-1.2.3.dist-info/WHEEL
frprint-1.2.3.dist-info/top_level.txt
frprint-1.2.3.dist-info/RECORD
