Metadata-Version: 2.4
Name: frprint
Version: 1.2.3
Summary: more easier to use for-print
Author-email: howShouldIChosseMyUsername <trademark2179@gmail.com>
License: MIT
Requires-Python: >=3.7
